pylena/CMakeLists.txt
pylena/__init__.py
pylena/_version.py
pylena/module.cpp
pylena/pylena_cxx.cpython-39-x86_64-linux-gnu.so
pylena/utils.py
pylena/include/pln/image_cast.hpp
pylena/lib/libpylene-numpy.a
pylena/morpho/CMakeLists.txt
pylena/morpho/__init__.py
pylena/morpho/_dahu.py
pylena/morpho/component_tree.py
pylena/morpho/maxtree.cpp
pylena/morpho/maxtree.hpp
pylena/morpho/morpho.cpp
pylena/morpho/morpho.hpp
pylena/morpho/se.cpp
pylena/morpho/se.hpp
pylena/morpho/se.py
pylena/morpho/soperations.cpp
pylena/morpho/soperations.hpp
pylena/morpho/soperations.py
pylena/morpho/watershed.cpp
pylena/morpho/watershed.hpp
pylena/morpho/watershed.py
pylena/scribo/CMakeLists.txt
pylena/scribo/__init__.py
pylena/scribo/line_detector.cpp
pylena/scribo/line_detector.hpp
pylena/scribo/line_detector.py
pylena/scribo/scribo.cpp
pylena/scribo/scribo.hpp
pylena.libs/libtbb-359a1419.so.12.7
pylena.libs/libtbbmalloc-f9e5c5de.so.2.7
pylena-0.1.5.dist-info/METADATA
pylena-0.1.5.dist-info/WHEEL
pylena-0.1.5.dist-info/top_level.txt
pylena-0.1.5.dist-info/RECORD
pylena-0.1.5.dist-info/licenses/LICENSE
