Metadata-Version: 2.4
Name: pylena
Version: 0.1.5
Summary: Image processing library
Author-email: "EPITA Research Laboratory (LRE)" <baptiste.esteban@epita.fr>
License: Mozilla Public License Version 2.0
Project-URL: Bug Tracker, https://gitlab.lre.epita.fr/olena/pylena/-/issues
Project-URL: changelog, http://olena.pages.lre.epita.fr/pylena/changelog.html
Project-URL: documentation, http://olena.pages.lre.epita.fr/pylena/
Project-URL: homepage, http://olena.pages.lre.epita.fr/pylena/
Project-URL: repository, https://gitlab.lre.epita.fr/olena/pylena
Platform: linux
Classifier: License :: OSI Approved :: Mozilla Public License 2.0 (MPL 2.0)
Classifier: Operating System :: POSIX :: Linux
Classifier: Programming Language :: C++
Classifier: Programming Language :: Python :: 3
Classifier: Programming Language :: Python :: 3 :: Only
Classifier: Programming Language :: Python :: Implementation :: CPython
Classifier: Topic :: Scientific/Engineering :: Image Processing
Requires-Python: >=3.9
License-File: LICENSE
Requires-Dist: numpy>=2
Requires-Dist: numba
Provides-Extra: doc
Requires-Dist: sphinx; extra == "doc"
Requires-Dist: sphinx_rtd_theme; extra == "doc"
Requires-Dist: sphinx_gallery; extra == "doc"
Requires-Dist: scikit-image; extra == "doc"
Requires-Dist: matplotlib; extra == "doc"
Requires-Dist: imagecodecs>=2021.11.20; extra == "doc"
Requires-Dist: pandas; extra == "doc"
Requires-Dist: sphinxcontrib-bibtex; extra == "doc"
Provides-Extra: packaging
Requires-Dist: auditwheel; extra == "packaging"
Requires-Dist: patchelf; extra == "packaging"
Provides-Extra: tests
Requires-Dist: pytest; extra == "tests"
Dynamic: license-file
Dynamic: platform
